bls_data/__init__.py
bls_data/bls.py
bls_data/data/area_titles.csv
bls_data/data/la_area.csv
bls_data/data/oes_areas.csv
bls_data-0.0.2.dist-info/LICENSE.txt
bls_data-0.0.2.dist-info/METADATA
bls_data-0.0.2.dist-info/WHEEL
bls_data-0.0.2.dist-info/top_level.txt
bls_data-0.0.2.dist-info/RECORD
