Metadata-Version: 2.1
Name: bls-data
Version: 0.0.2
Summary: A Python library to parse and visualize Bureau of Labor Statistics Data
Home-page: https://github.com/a-finocchiaro/bls-data
Author: Aaron Finocchiaro
Author-email: afinny10@gmail.com
License: UNKNOWN
Download-URL: https://github.com/a-finocchiaro/bls-data/archive/refs/tags/0.0.1.zip
Keywords: Pandas,Bureau,Labor,Statistics,Plotly
Platform: UNKNOWN
Classifier: Programming Language :: Python :: 3
Classifier: License :: OSI Approved :: MIT License
Classifier: Operating System :: OS Independent
Requires-Python: >=3.7
License-File: LICENSE.txt
Requires-Dist: pandas
Requires-Dist: plotly
Requires-Dist: requests
